{"acrossmap":null,"admin":false,"answers":{"across":["CASCA","AMY","BLIP","TREAT","WEE","PRADO","REALM","MTA","ROVES","ALLFLASHNOCASH","MEIN","IFC","SATEEN","NOTFORME","ICH","DOOR","ELIAS","THATCANTBERIGHT","BONZO","URSA","IRE","YOGAPOSE","TRADER","TOO","RUED","JAZZUPTHEPLACE","IQUIT","OOH","IGAVE","LUCKS","MBA","EIDER","TIKI","BOB","FOSSE"],"down":["CTR","AREA","SEAL","CALLME","ATMFEE","AWMAN","METS","YEAH","BROCCOLI","LAVA","IDES","POSH","PROFFER","LINDA","NIT","SITBY","ACHOO","THANG","NOTRE","ORBS","RIGID","MAHRE","ESTER","ONUS","TZATZIKI","COPOUTS","EATUP","OOP","RELIEF","ADAGIO","REHAB","JILT","AQUI","ZUCK","TOMB","HOBO","CADS","EVES","ERE"]},"author":"Natasha Lyonne and Deb Amlen","autowrap":null,"bbars":null,"circles":null,"clues":{"across":["1. Who says &quot;Speak, hands, for me!&quot; in &quot;Julius Caesar&quot;","6. Poehler vortex of funniness?","9. It might be on one's radar","13. Reward for Fido","14. Tiny","15. Where to enjoy a Goya","16. Queen's domain","17. N.Y.C. subway overseer","18. Wanders","19. Dressed like &quot;a hundred-dollar millionaire&quot;","22. Lo ___ (Chinese noodle dish)","23. &quot;Portlandia&quot; airer","24. Glossy fabric","27. &quot;I'll pass&quot;","32. &quot;___ bin ein Berliner&quot;","33. It might have golden locks","35. Howe he could invent!","36. &quot;I think I made a mistake here&quot;","40. &quot;Bedtime for ___&quot;","41. Celestial bear","42. Rage","43. Downward-Facing Dog, e.g.","45. Merchant","48. #Me___","49. Felt remorse for","50. &quot;Add some throw pillows or a pop of color around here, why don't you!&quot;","57. Parting words","58. Aah's partner","59. Words on some blood drive stickers","61. Is very fortunate, with &quot;out&quot;","62. Wharton grad","63. Creature to get down from","64. Polynesian carving","65. With 66-Across, choreographer whose life is depicted in the starts of 19-, 36- and 50-Across","66. See 65-Across"],"down":["1. Middle: Abbr.","2. The &quot;A&quot; in BART","3. Animal having a ball at the circus?","4. 1980 Blondie hit","5. Cost of withdrawing, say","6. &quot;Gee, you're killin' me!&quot;","7. Baseball's &quot;Amazin's&quot;","8. When sung three times, what follows &quot;She loves you&quot;","9. Vegetable with a head","10. Volcano's spew","11. Fateful day for Caesar","12. Deluxe","15. Present for acceptance","20. Actress Blair of &quot;The Exorcist&quot;","21. It can be picked","24. Remain idle","25. Sound during hay fever season","26. Dr. Dre's &quot;Nuthin' but a 'G' ___&quot;","27. Our, in Orléans","28. Sun, moon and stars","29. Unbending","30. Phil ___, slalom skiing gold medalist at the 1984 Olympics","31. Fragrant compound","34. Cross to bear","37. Greek sauce with yogurt and cucumbers","38. Bad rationalizations","39. Gobble","44. &quot;Alley ___!&quot;","46. Analgesic's promise","47. Slow, in music","49. Where one might kick a habit, informally","50. Ghost at the altar?","51. Here, in Madrid","52. Facebook founder's nickname","53. Taj Mahal, e.g.","54. King of the road","55. Untrustworthy types","56. After-work times, in classifieds","60. &quot;Able was I ___ I saw Elba&quot;"]},"code":null,"copyright":"2019, The New York Times","date":"4\/2\/2019","dow":"Tuesday","downmap":null,"editor":"Will Shortz","grid":["C","A","S","C","A",".","A","M","Y",".",".","B","L","I","P","T","R","E","A","T",".","W","E","E",".","P","R","A","D","O","R","E","A","L","M",".","M","T","A",".","R","O","V","E","S",".","A","L","L","F","L","A","S","H","N","O","C","A","S","H",".",".",".","M","E","I","N",".",".","I","F","C",".",".",".","S","A","T","E","E","N",".","N","O","T","F","O","R","M","E","I","C","H",".",".","D","O","O","R",".","E","L","I","A","S","T","H","A","T","C","A","N","T","B","E","R","I","G","H","T","B","O","N","Z","O",".","U","R","S","A",".",".","I","R","E","Y","O","G","A","P","O","S","E",".","T","R","A","D","E","R",".",".",".","T","O","O",".",".","R","U","E","D",".",".",".","J","A","Z","Z","U","P","T","H","E","P","L","A","C","E",".","I","Q","U","I","T",".","O","O","H",".","I","G","A","V","E","L","U","C","K","S",".","M","B","A",".","E","I","D","E","R","T","I","K","I",".",".","B","O","B",".","F","O","S","S","E"],"gridnums":[1,2,3,4,5,0,6,7,8,0,0,9,10,11,12,13,0,0,0,0,0,14,0,0,0,15,0,0,0,0,16,0,0,0,0,0,17,0,0,0,18,0,0,0,0,0,19,0,0,0,20,0,0,0,21,0,0,0,0,0,0,0,0,22,0,0,0,0,0,23,0,0,0,0,0,24,25,26,0,0,0,0,27,28,0,0,0,29,30,31,32,0,0,0,0,33,34,0,0,0,35,0,0,0,0,36,0,0,37,38,0,0,0,0,39,0,0,0,0,0,40,0,0,0,0,0,41,0,0,0,0,0,42,0,0,43,0,0,0,0,44,0,0,0,45,46,47,0,0,0,0,0,0,48,0,0,0,0,49,0,0,0,0,0,0,50,51,52,0,0,0,53,54,0,0,0,0,55,56,0,57,0,0,0,0,0,58,0,0,0,59,0,0,0,60,61,0,0,0,0,0,62,0,0,0,63,0,0,0,0,64,0,0,0,0,0,65,0,0,0,66,0,0,0,0],"hastitle":false,"hold":null,"id":null,"id2":null,"interpretcolors":null,"jnotes":"<p><a href=\"https:\/\/www.nytimes.com\/2019\/04\/01\/reader-center\/natasha-lyonne-crossword-puzzle.html\">How Natasha Lyonne Created a Times Crossword Puzzle<\/a> &mdash; nice NYT article about her experience.<\/p>","key":null,"mini":null,"navigate":true,"notepad":"CELEBRITY CROSSWORD<br \/>This puzzle is a collaboration by the actress Natasha Lyonne of Netflix's \"Orange Is the New Black\" and \"Russian Doll,\" working together with Deb Amlen, who writes the Times's daily crossword column, Wordplay (nytimes.com\/column\/wordplay). You can read more about the making of today's puzzle there. This is Deb's fourth crossword for The Times.","publisher":"The New York Times","rbars":null,"shadecircles":null,"size":{"cols":15,"rows":15},"target":"\/Crossword?date=4\/2\/2019","title":"NY TIMES, TUE, APR 02, 2019","track":null,"type":null,"uniclue":false,"valid":true}